impaf-0.1.1.dist-info/DESCRIPTION.rst
impaf-0.1.1.dist-info/WHEEL
impaf-0.1.1.dist-info/RECORD
impaf-0.1.1.dist-info/top_level.txt
impaf-0.1.1.dist-info/metadata.json
impaf-0.1.1.dist-info/METADATA
impaf/requestable.py
impaf/utils.py
impaf/widget.py
impaf/__init__.py
impaf/routing.py
impaf/application.py
impaf/settings.py
impaf/testing/cache.py
impaf/testing/case.py
impaf/testing/__init__.py
impaf/testing/old.py
impaf/testing/dict.py
impaf/testing/__pycache__/old.cpython-35.pyc
impaf/testing/__pycache__/case.cpython-35.pyc
impaf/testing/__pycache__/dict.cpython-35.pyc
impaf/testing/__pycache__/cache.cpython-35.pyc
impaf/testing/__pycache__/__init__.cpython-35.pyc
impaf/tests/test_utils.py
impaf/tests/test_application.py
impaf/tests/__init__.py
impaf/tests/test_widget.py
impaf/tests/test_routing.py
impaf/tests/test_requestable.py
impaf/tests/test_settings.py
impaf/tests/__pycache__/test_routing.cpython-35-PYTEST.pyc
impaf/tests/__pycache__/test_settings.cpython-35-PYTEST.pyc
impaf/tests/__pycache__/test_widget.cpython-35-PYTEST.pyc
impaf/tests/__pycache__/test_requestable.cpython-35-PYTEST.pyc
impaf/tests/__pycache__/test_utils.cpython-35-PYTEST.pyc
impaf/tests/__pycache__/test_application.cpython-35-PYTEST.pyc
impaf/tests/__pycache__/__init__.cpython-35.pyc
impaf/controller/mechanics.py
impaf/controller/utils.py
impaf/controller/base.py
impaf/controller/__init__.py
impaf/controller/virtual.py
impaf/controller/exceptions.py
impaf/controller/json.py
impaf/controller/tests/test_json.py
impaf/controller/tests/__init__.py
impaf/controller/tests/test_controller.py
impaf/controller/tests/__pycache__/test_json.cpython-35-PYTEST.pyc
impaf/controller/tests/__pycache__/test_controller.cpython-35-PYTEST.pyc
impaf/controller/tests/__pycache__/__init__.cpython-35.pyc
impaf/controller/__pycache__/virtual.cpython-35.pyc
impaf/controller/__pycache__/json.cpython-35.pyc
impaf/controller/__pycache__/base.cpython-35.pyc
impaf/controller/__pycache__/utils.cpython-35.pyc
impaf/controller/__pycache__/exceptions.cpython-35.pyc
impaf/controller/__pycache__/mechanics.cpython-35.pyc
impaf/controller/__pycache__/__init__.cpython-35.pyc
