Metadata-Version: 2.0
Name: impaf
Version: 0.1.1
Summary: Inherit Me Please Anti Framework
Home-page: https://github.com/socek/impaf
Author: UNKNOWN
Author-email: UNKNOWN
License: Apache License 2.0
Platform: UNKNOWN
Requires-Dist: pyramid
Requires-Dist: morfdict (>=0.3.7)
Requires-Dist: pytest-cov
Requires-Dist: pytest
Requires-Dist: sphinx
Requires-Dist: pyyaml
Requires-Dist: mock
